[
    {
        "key": "dbln",
        "value": "%7B%2261567938668419%22%3A%2204aMjGzl%22%2C%2261558251510273%22%3A%22X2DWWU2y%22%2C%2261568615729158%22%3A%22JnynxYic%22%7D",
        "domain": "facebook.com",
        "path": "/login/device-based/",
        "hostOnly": false,
        "creation": "2024-11-25T10:43:40.631Z",
        "lastAccessed": "2024-11-25T10:43:40.631Z"
    },
    {
        "key": "datr",
        "value": "GKEvZ3ViQgKhGhqIds_pi5Jw",
        "domain": "facebook.com",
        "path": "/",
        "hostOnly": false,
        "creation": "2024-11-25T10:43:40.631Z",
        "lastAccessed": "2024-11-25T10:43:40.631Z"
    },
    {
        "key": "sb",
        "value": "GKEvZ41U0qgjGf3oPDSxRb29",
        "domain": "facebook.com",
        "path": "/",
        "hostOnly": false,
        "creation": "2024-11-25T10:43:40.631Z",
        "lastAccessed": "2024-11-25T10:43:40.631Z"
    },
    {
        "key": "vpd",
        "value": "v1%3B494x266x2.701960802078247",
        "domain": "facebook.com",
        "path": "/",
        "hostOnly": false,
        "creation": "2024-11-25T10:43:40.631Z",
        "lastAccessed": "2024-11-25T10:43:40.631Z"
    },
    {
        "key": "ps_l",
        "value": "1",
        "domain": "facebook.com",
        "path": "/",
        "hostOnly": false,
        "creation": "2024-11-25T10:43:40.631Z",
        "lastAccessed": "2024-11-25T10:43:40.631Z"
    },
    {
        "key": "ps_n",
        "value": "1",
        "domain": "facebook.com",
        "path": "/",
        "hostOnly": false,
        "creation": "2024-11-25T10:43:40.631Z",
        "lastAccessed": "2024-11-25T10:43:40.631Z"
    },
    {
        "key": "m_pixel_ratio",
        "value": "2.701960802078247",
        "domain": "facebook.com",
        "path": "/",
        "hostOnly": false,
        "creation": "2024-11-25T10:43:40.631Z",
        "lastAccessed": "2024-11-25T10:43:40.631Z"
    },
    {
        "key": "wd",
        "value": "266x494",
        "domain": "facebook.com",
        "path": "/",
        "hostOnly": false,
        "creation": "2024-11-25T10:43:40.631Z",
        "lastAccessed": "2024-11-25T10:43:40.631Z"
    },
    {
        "key": "c_user",
        "value": "61568615729158",
        "domain": "facebook.com",
        "path": "/",
        "hostOnly": false,
        "creation": "2024-11-25T10:43:40.631Z",
        "lastAccessed": "2024-11-25T10:43:40.631Z"
    },
    {
        "key": "fr",
        "value": "0cEoDtRxKONuRk8kM.AWVREC8XRsu9uWI_drc2SnqRrBY.BnQBxs..AAA.0.0.BnRFSK.AWWPuT9BUS8",
        "domain": "facebook.com",
        "path": "/",
        "hostOnly": false,
        "creation": "2024-11-25T10:43:40.631Z",
        "lastAccessed": "2024-11-25T10:43:40.631Z"
    },
    {
        "key": "xs",
        "value": "42%3AsTK9ZNECBAmphA%3A2%3A1732531339%3A-1%3A-1",
        "domain": "facebook.com",
        "path": "/",
        "hostOnly": false,
        "creation": "2024-11-25T10:43:40.631Z",
        "lastAccessed": "2024-11-25T10:43:40.631Z"
    },
    {
        "key": "locale",
        "value": "hi_IN",
        "domain": "facebook.com",
        "path": "/",
        "hostOnly": false,
        "creation": "2024-11-25T10:43:40.631Z",
        "lastAccessed": "2024-11-25T10:43:40.631Z"
    },
    {
        "key": "fbl_st",
        "value": "101228996%3BT%3A28875522",
        "domain": "facebook.com",
        "path": "/",
        "hostOnly": false,
        "creation": "2024-11-25T10:43:40.631Z",
        "lastAccessed": "2024-11-25T10:43:40.631Z"
    },
    {
        "key": "wl_cbv",
        "value": "v2%3Bclient_version%3A2681%3Btimestamp%3A1732531347%3BCRCM%3A-1927477717",
        "domain": "facebook.com",
        "path": "/",
        "hostOnly": false,
        "creation": "2024-11-25T10:43:40.631Z",
        "lastAccessed": "2024-11-25T10:43:40.631Z"
    }
]
